xprogress/__init__.py
xprogress/xprogress.py
xprogress-0.4.dist-info/LICENSE
xprogress-0.4.dist-info/METADATA
xprogress-0.4.dist-info/WHEEL
xprogress-0.4.dist-info/top_level.txt
xprogress-0.4.dist-info/RECORD
