Metadata-Version: 2.1
Name: xprogress
Version: 0.4
Summary: Extremely simple progressbar
Home-page: https://github.com/thyeem/xprogress
Author: Francis Lim
Author-email: thyeem@gmail.com
License: UNKNOWN
Keywords: xprogress,progress,progressbar
Platform: UNKNOWN
Requires-Python: >=3.6
